api_deezer_full/__init__.py
api_deezer_full/gw/__init__.py
api_deezer_full/gw/api.py
api_deezer_full/gw/decorators/__init__.py
api_deezer_full/gw/decorators/login.py
api_deezer_full/gw/exceptions/__init__.py
api_deezer_full/gw/exceptions/arl_invalid.py
api_deezer_full/gw/exceptions/track_404.py
api_deezer_full/gw/types/__init__.py
api_deezer_full/gw/types/album.py
api_deezer_full/gw/types/artist.py
api_deezer_full/gw/types/contributor.py
api_deezer_full/gw/types/playlist.py
api_deezer_full/gw/types/search/__init__.py
api_deezer_full/gw/types/search/album.py
api_deezer_full/gw/types/search/artist.py
api_deezer_full/gw/types/search/playlist.py
api_deezer_full/gw/types/search/search.py
api_deezer_full/gw/types/track.py
api_deezer_full/gw/types/user.py
api_deezer_full/gw/utils.py
api_deezer_full/media/__init__.py
api_deezer_full/media/api.py
api_deezer_full/media/exceptions/__init__.py
api_deezer_full/media/exceptions/insufficient_rights.py
api_deezer_full/media/types/__init__.py
api_deezer_full/media/types/aliases.py
api_deezer_full/media/types/cipher.py
api_deezer_full/media/types/media.py
api_deezer_full/media/types/medias.py
api_deezer_full/media/types/source.py
api_deezer_full/mobile/__init__.py
api_deezer_full/mobile/api.py
api_deezer_full/mobile/exceptions/__init__.py
api_deezer_full/mobile/exceptions/bad_credentials.py
api_deezer_full/mobile/utils.py
api_deezer_full/pipe/__init__.py
api_deezer_full/pipe/api.py
api_deezer_full/pipe/decorators/__init__.py
api_deezer_full/pipe/decorators/login.py
api_deezer_full/pipe/grapql/__init__.py
api_deezer_full/pipe/grapql/queries.py
api_deezer_full/pipe/grapql/types.py
api_deezer_full/pipe/types/__init__.py
api_deezer_full/pipe/types/album.py
api_deezer_full/pipe/types/artist.py
api_deezer_full/pipe/types/bases.py
api_deezer_full/pipe/types/contributor.py
api_deezer_full/pipe/types/cover.py
api_deezer_full/pipe/types/disk_info.py
api_deezer_full/pipe/types/lyrics.py
api_deezer_full/pipe/types/media.py
api_deezer_full-0.0.1b41.dist-info/METADATA
api_deezer_full-0.0.1b41.dist-info/WHEEL
api_deezer_full-0.0.1b41.dist-info/RECORD
