Metadata-Version: 2.3
Name: api-deezer-full
Version: 0.0.1b41
Summary: Wrapper for all 'hidden' deezer APIs
License: CC BY 4.0
Author: An0nimia
Author-email: an0nimia@protonmail.com
Requires-Python: >=3.12,<4.0
Classifier: License :: Other/Proprietary License
Classifier: Programming Language :: Python :: 3
Classifier: Programming Language :: Python :: 3.12
Classifier: Programming Language :: Python :: 3.13
Requires-Dist: pycryptodomex (>=3.21.0,<4.0.0)
Requires-Dist: pydantic (>=2.4.1,<3.0.0)
Requires-Dist: pyjwt (>=2.8.0,<3.0.0)
Requires-Dist: requests (>=2.32.0,<3.0.0)
